integration_test/__init__.py
integration_test/base.py
integration_test/test_certs.py
integration_test/test_legacy.py
integration_test/test_other.py
integration_test/test_users.py
mtls_server/__init__.py
mtls_server/auth.py
mtls_server/cert_processor.py
mtls_server/config.py
mtls_server/handler.py
mtls_server/key_refresh.py
mtls_server/logger.py
mtls_server/server.py
mtls_server/storage.py
mtls_server/sync.py
mtls_server/utils.py
mtls_server/wsgi.py
mtls_server-0.20.0.dist-info/LICENSE
mtls_server-0.20.0.dist-info/METADATA
mtls_server-0.20.0.dist-info/WHEEL
mtls_server-0.20.0.dist-info/entry_points.txt
mtls_server-0.20.0.dist-info/top_level.txt
mtls_server-0.20.0.dist-info/zip-safe
mtls_server-0.20.0.dist-info/RECORD
