Metadata-Version: 2.1
Name: mtls-server
Version: 0.20.0
Summary: A short-lived certificate tool based on the Zero Trust network mode
Home-page: https://github.com/drGrove/mtls-server
Author: Danny Grove
Author-email: danny@drgrovellc.com
License: UNKNOWN
Project-URL: Homepage, https://github.com/drGrove/mtls-server
Project-URL: Source, https://github.com/drGrove/mtls-server
Project-URL: Tracker, https://github.com/drGrove/mtls-server/issues
Platform: UNKNOWN
Classifier: Development Status :: 4 - Beta
Classifier: Intended Audience :: Developers
Classifier: Intended Audience :: System Administrators
Classifier: License :: OSI Approved :: Apache Software License
Classifier: Operating System :: OS Independent
Classifier: Topic :: Internet
Classifier: Topic :: Security :: Cryptography
Classifier: Topic :: Security
Classifier: Topic :: Software Development :: Libraries :: Python Modules
Classifier: Programming Language :: Python :: 3
Classifier: Programming Language :: Python :: 3.6
Classifier: Programming Language :: Python :: 3 :: Only
Requires-Python: >=3.6
License-File: LICENSE
Requires-Dist: Flask
Requires-Dist: Jinja2
Requires-Dist: cryptography
Requires-Dist: psycopg2-binary
Requires-Dist: python-gnupg
Requires-Dist: uWSGI
